aoi_simulator/__init__.py
aoi_simulator/core/AoIAgent.py
aoi_simulator/core/AoICalc.py
aoi_simulator/core/AoIQueueNetwork.py
aoi_simulator/queues/AoIQueueServer.py
aoi_simulator/queues/LcfsPreemption.py
aoi_simulator/queues/LgfsMultiServerNoPreemption.py
aoi_simulator/queues/LgfsMultiServerPreemption.py
aoi_simulator/queues/LgfsMultiServerPreemptionW.py
aoi_simulator/queues/LgfsPreemption.py
aoi_simulator-0.3.3.dist-info/LICENSE
aoi_simulator-0.3.3.dist-info/METADATA
aoi_simulator-0.3.3.dist-info/WHEEL
aoi_simulator-0.3.3.dist-info/top_level.txt
aoi_simulator-0.3.3.dist-info/RECORD
