Metadata-Version: 2.1
Name: aoi-simulator
Version: 0.3.3
Summary: Age of Information simulation package
Home-page: https://github.com/pprandel/aoi-simulator
Author: Paulo Prandel
Author-email: pauloprandel@hotmail.com
License: UNKNOWN
Project-URL: Bug Tracker, https://github.com/pprandel/aoi-simulator/issues
Platform: UNKNOWN
Classifier: Programming Language :: Python :: 3
Classifier: License :: OSI Approved :: MIT License
Classifier: Operating System :: OS Independent
Requires-Python: >=3.7
License-File: LICENSE
Requires-Dist: aoi-queueing-tool (>=1.2.4)
Requires-Dist: matplotlib (>=3.3.4)
Requires-Dist: scipy (>=1.5.4)
Requires-Dist: reliability (>=0.5.7)
